ssh_client/__init__.py
ssh_client/config.py
ssh_client/helpers.py
ssh_client/main.py
ssh_client/remote_client.py
ssh_client/ssh_client.py
ssh_client/test.py
ssh_client/bats/check.bat
ssh_client/bats/setup.bat
tests/__init__.py
canper_ssh_client-0.3.7.dist-info/METADATA
canper_ssh_client-0.3.7.dist-info/WHEEL
canper_ssh_client-0.3.7.dist-info/top_level.txt
canper_ssh_client-0.3.7.dist-info/RECORD
