Metadata-Version: 2.1
Name: canper-ssh-client
Version: 0.3.7
Summary: Perform operations in client
Home-page: UNKNOWN
Author: Diego
Author-email: diego@test.com
License: MIT
Platform: UNKNOWN
Requires-Python: >=3.7.7
Requires-Dist: paramiko (==2.7.1)
Requires-Dist: scp (==0.13.2)
Requires-Dist: python-dateutil (==2.8.1)
